pyats/aetest/__init__.py
pyats/aetest/__main__.cpython-313-x86_64-linux-gnu.so
pyats/aetest/base.cpython-313-x86_64-linux-gnu.so
pyats/aetest/commons.cpython-313-x86_64-linux-gnu.so
pyats/aetest/container.cpython-313-x86_64-linux-gnu.so
pyats/aetest/discovery.cpython-313-x86_64-linux-gnu.so
pyats/aetest/exceptions.cpython-313-x86_64-linux-gnu.so
pyats/aetest/function.cpython-313-x86_64-linux-gnu.so
pyats/aetest/loop.cpython-313-x86_64-linux-gnu.so
pyats/aetest/main.cpython-313-x86_64-linux-gnu.so
pyats/aetest/parameters.cpython-313-x86_64-linux-gnu.so
pyats/aetest/retry.cpython-313-x86_64-linux-gnu.so
pyats/aetest/script.cpython-313-x86_64-linux-gnu.so
pyats/aetest/sections.cpython-313-x86_64-linux-gnu.so
pyats/aetest/signals.cpython-313-x86_64-linux-gnu.so
pyats/aetest/testcase.cpython-313-x86_64-linux-gnu.so
pyats/aetest/datafile/__init__.py
pyats/aetest/datafile/loader.cpython-313-x86_64-linux-gnu.so
pyats/aetest/datafile/markup.cpython-313-x86_64-linux-gnu.so
pyats/aetest/datafile/schema.cpython-313-x86_64-linux-gnu.so
pyats/aetest/executer/__init__.py
pyats/aetest/executer/implementation.cpython-313-x86_64-linux-gnu.so
pyats/aetest/processors/__init__.py
pyats/aetest/processors/bases.cpython-313-x86_64-linux-gnu.so
pyats/aetest/processors/decorator.cpython-313-x86_64-linux-gnu.so
pyats/aetest/processors/exceptions.cpython-313-x86_64-linux-gnu.so
pyats/aetest/processors/filters.cpython-313-x86_64-linux-gnu.so
pyats/aetest/processors/handler.cpython-313-x86_64-linux-gnu.so
pyats/aetest/processors/signals.cpython-313-x86_64-linux-gnu.so
pyats/aetest/processors/skips.cpython-313-x86_64-linux-gnu.so
pyats/aetest/processors/store.cpython-313-x86_64-linux-gnu.so
pyats/aetest/processors/wrappers.cpython-313-x86_64-linux-gnu.so
pyats/aetest/reporter/__init__.py
pyats/aetest/reporter/aereport.cpython-313-x86_64-linux-gnu.so
pyats/aetest/reporter/base.cpython-313-x86_64-linux-gnu.so
pyats/aetest/reporter/default.cpython-313-x86_64-linux-gnu.so
pyats.aetest-25.9.dist-info/METADATA
pyats.aetest-25.9.dist-info/WHEEL
pyats.aetest-25.9.dist-info/top_level.txt
pyats.aetest-25.9.dist-info/RECORD
